bai_file_processor/__init__.py
bai_file_processor/bai_parser.py
bai_file_processor/constants.py
bai_file_processor/exceptions.py
bai_file_processor/helpers.py
bai_file_processor/models.py
bai_file_processor/parsers.py
bai_file_processor/utils.py
bai_file_processor/writers.py
bai_file_processor-1.0.0.dist-info/LICENSE
bai_file_processor-1.0.0.dist-info/LICENSE.txt
bai_file_processor-1.0.0.dist-info/METADATA
bai_file_processor-1.0.0.dist-info/WHEEL
bai_file_processor-1.0.0.dist-info/top_level.txt
bai_file_processor-1.0.0.dist-info/RECORD
