Metadata-Version: 2.1
Name: bai-file-processor
Version: 1.0.0
Summary: BAI File Parser
Home-page: https://github.com/ankurCES/bai-file-processor
Author: Ankur Nair
Author-email: ankur.nair@cesltd.com
License: MIT
Keywords: BAI bookkeeping cash management balance reporting
Platform: UNKNOWN
Classifier: Development Status :: 4 - Beta
Classifier: Intended Audience :: Developers
Classifier: License :: OSI Approved :: MIT License
Classifier: Natural Language :: English
Classifier: Operating System :: OS Independent
Classifier: Programming Language :: Python :: 3
Classifier: Programming Language :: Python :: 3.6
Classifier: Programming Language :: Python :: 3.7
Classifier: Programming Language :: Python :: 3.8
